[
  {
    "orderID": "ODR1546",
    "vendorName": "Nirvana Restaurant",
    "status": "Shipped",
    "pickUpDate": "2023-05-01"
  },
  {
    "orderID": "ODR3247",
    "vendorName": "Guru Kripa Restaurant",
    "status": "Cancelled",
    "pickUpDate": "2023-05-03"
  },
  {
    "orderID": "ODR7638",
    "vendorName": "Moti Mahal Delux",
    "status": "Pending",
    "pickUpDate": "2023-05-02"
  },
  {
    "orderID": "ODR5328",
    "vendorName": "Bikanervala",
    "status": "Shipped",
    "pickUpDate": "2023-05-04"
  },
  {
    "orderID": "ODR8239",
    "vendorName": "Haldiram's",
    "status": "Cancelled",
    "pickUpDate": "2023-05-05"
  },
  {
    "orderID": "ODR3475",
    "vendorName": "Nirvana Restaurant",
    "status": "Shipped",
    "pickUpDate": "2023-05-06"
  },
  {
    "orderID": "ODR4927",
    "vendorName": "Moti Mahal Delux",
    "status": "Pending",
    "pickUpDate": "2023-05-07"
  },
  {
    "orderID": "ODR7292",
    "vendorName": "Bikanervala",
    "status": "Shipped",
    "pickUpDate": "2023-05-08"
  },
  {
    "orderID": "ODR2349",
    "vendorName": "Guru Kripa Restaurant",
    "status": "Cancelled",
    "pickUpDate": "2023-05-09"
  },
  {
    "orderID": "ODR7238",
    "vendorName": "Nirvana Restaurant",
    "status": "Pending",
    "pickUpDate": "2023-05-10"
  },
  {
    "orderID": "ODR3948",
    "vendorName": "Moti Mahal Delux",
    "status": "Shipped",
    "pickUpDate": "2023-05-11"
  },
  {
    "orderID": "ODR5942",
    "vendorName": "Bikanervala",
    "status": "Cancelled",
    "pickUpDate": "2023-05-12"
  },
  {
    "orderID": "ODR7245",
    "vendorName": "Haldiram's",
    "status": "Shipped",
    "pickUpDate": "2023-05-13"
  },
  {
    "orderID": "ODR8947",
    "vendorName": "Nirvana Restaurant",
    "status": "Cancelled",
    "pickUpDate": "2023-05-14"
  },
  {
    "orderID": "ODR2364",
    "vendorName": "Moti Mahal Delux",
    "status": "Pending",
    "pickUpDate": "2023-05-15"
  },
  {
    "orderID": "ODR2345",
    "vendorName": "Sharma Sweets",
    "status": "Shipped",
    "pickUpDate": "2023-04-16"
  },
  {
    "orderID": "ODR8374",
    "vendorName": "Rajesh Masala",
    "status": "Cancelled",
    "pickUpDate": "2023-04-15"
  },
  {
    "orderID": "ODR4928",
    "vendorName": "Singh Caterers",
    "status": "Pending",
    "pickUpDate": "2023-04-18"
  },
  {
    "orderID": "ODR6239",
    "vendorName": "Sharma Sweets",
    "status": "Shipped",
    "pickUpDate": "2023-04-19"
  },
  {
    "orderID": "ODR3476",
    "vendorName": "Rajesh Masala",
    "status": "Pending",
    "pickUpDate": "2023-04-20"
  },
  {
    "orderID": "ODR9847",
    "vendorName": "Singh Caterers",
    "status": "Shipped",
    "pickUpDate": "2023-04-16"
  },
  {
    "orderID": "ODR2756",
    "vendorName": "Sharma Sweets",
    "status": "Cancelled",
    "pickUpDate": "2023-04-17"
  },
  {
    "orderID": "ODR7392",
    "vendorName": "Rajesh Masala",
    "status": "Pending",
    "pickUpDate": "2023-04-19"
  },
  {
    "orderID": "ODR8235",
    "vendorName": "Singh Caterers",
    "status": "Shipped",
    "pickUpDate": "2023-04-21"
  },
  {
    "orderID": "ODR4628",
    "vendorName": "Sharma Sweets",
    "status": "Shipped",
    "pickUpDate": "2023-04-18"
  },
  {
    "orderID": "ODR8378",
    "vendorName": "Rajesh Masala",
    "status": "Cancelled",
    "pickUpDate": "2023-04-15"
  },
  {
    "orderID": "ODR5473",
    "vendorName": "Rajasthan Sweets",
    "status": "Pending",
    "pickUpDate": "2023-04-20"
  },
  {
    "orderID": "ODR3645",
    "vendorName": "Singh Caterers",
    "status": "Shipped",
    "pickUpDate": "2023-04-17"
  },
  {
    "orderID": "ODR7293",
    "vendorName": "Sharma Sweets",
    "status": "Cancelled",
    "pickUpDate": "2023-04-22"
  },
  {
    "orderID": "ODR8426",
    "vendorName": "Rajesh Masala",
    "status": "Pending",
    "pickUpDate": "2023-04-23"
  },
  {
    "orderID": "ODR1597",
    "vendorName": "Singh Caterers",
    "status": "Shipped",
    "pickUpDate": "2023-04-23"
  },
  {
    "orderID": "ODR4726",
    "vendorName": "Guru Kripa Restaurant",
    "status": "Shipped",
    "pickUpDate": "2023-05-16"
  },
  {
    "orderID": "ODR8234",
    "vendorName": "Haldiram's",
    "status": "Cancelled",
    "pickUpDate": "2023-05-17"
  },
  {
    "orderID": "ODR2753",
    "vendorName": "Nirvana Restaurant",
    "status": "Pending",
    "pickUpDate": "2023-05-18"
  },
  {
    "orderID": "ODR5839",
    "vendorName": "Bikanervala",
    "status": "Shipped",
    "pickUpDate": "2023-05-19"
  },
  {
    "orderID": "ODR9238",
    "vendorName": "Moti Mahal Delux",
    "status": "Cancelled",
    "pickUpDate": "2023-05-20"
  },
  {
    "orderID": "ODR4837",
    "vendorName": "Guru Kripa Restaurant",
    "status": "Shipped",
    "pickUpDate": "2023-05-21"
  },
  {
    "orderID": "ODR7294",
    "vendorName": "Bikanervala",
    "status": "Pending",
    "pickUpDate": "2023-05-22"
  },
  {
    "orderID": "ODR9476",
    "vendorName": "Nirvana Restaurant",
    "status": "Shipped",
    "pickUpDate": "2023-05-23"
  },
  {
    "orderID": "ODR3752",
    "vendorName": "Moti Mahal Delux",
    "status": "Cancelled",
    "pickUpDate": "2023-05-24"
  },
  {
    "orderID": "ODR2495",
    "vendorName": "Haldiram's",
    "status": "Pending",
    "pickUpDate": "2023-05-25"
  },
  {
    "orderID": "ODR3765",
    "vendorName": "Nirvana Restaurant",
    "status": "Shipped",
    "pickUpDate": "2023-05-26"
  },
  {
    "orderID": "ODR9352",
    "vendorName": "Guru Kripa Restaurant",
    "status": "Cancelled",
    "pickUpDate": "2023-05-27"
  },
  {
    "orderID": "ODR5275",
    "vendorName": "Bikanervala",
    "status": "Pending",
    "pickUpDate": "2023-05-28"
  },
  {
    "orderID": "ODR7426",
    "vendorName": "Moti Mahal Delux",
    "status": "Shipped",
    "pickUpDate": "2023-05-29"
  },
  {
    "orderID": "ODR2385",
    "vendorName": "Haldiram's",
    "status": "Cancelled",
    "pickUpDate": "2023-05-30"
  }
]
